NLPpackage
