Metadata-Version: 1.0
Name: NLPpackage-Package
Version: 1.3
Summary: udacity ND
Home-page: UNKNOWN
Author: Stefan Ludmann
Author-email: UNKNOWN
License: UNKNOWN
Platform: UNKNOWN
